o3.py
o3-0.4.2.dist-info/LICENSE
o3-0.4.2.dist-info/METADATA
o3-0.4.2.dist-info/WHEEL
o3-0.4.2.dist-info/top_level.txt
o3-0.4.2.dist-info/RECORD
