Metadata-Version: 2.1
Name: o3
Version: 0.4.2
Author-email: Oz N Tiram <oz.tiram@gmail.com>
Project-URL: homepage, https://gitlab.com/oz123/o3
Classifier: Development Status :: 3 - Alpha
Classifier: Programming Language :: Python
Classifier: Programming Language :: Python :: 3.9
Classifier: Programming Language :: Python :: 3.10
Classifier: Programming Language :: Python :: 3.11
Classifier: Intended Audience :: System Administrators
Classifier: Intended Audience :: Developers
Classifier: Operating System :: OS Independent
Classifier: License :: OSI Approved :: GNU Lesser General Public License v3 or later (LGPLv3+)
Classifier: Topic :: Software Development
License-File: LICENSE
